itint/__init__.py
itint/assets_rc.py
itint/main.py
itint/octree.py
itint/pyside_compile.py
itint/ui_color_display.py
itint/ui_color_selector.py
itint/ui_widget.py
itint/utils.py
itint/widget.py
itint/widget_color_display.py
itint/widget_color_selector.py
itint/widget_screen_color_picker.py
itint/widget_screenshot.py
iTint-0.0.1.dist-info/METADATA
iTint-0.0.1.dist-info/WHEEL
iTint-0.0.1.dist-info/entry_points.txt
iTint-0.0.1.dist-info/top_level.txt
iTint-0.0.1.dist-info/RECORD
