Metadata-Version: 2.1
Name: iTint
Version: 0.0.1
Summary: A theme color extraction widget based on octree with multiple inputs (file, screen).
Home-page: https://github.com/ColorsWind/iTint
Author: ColorsWind
Author-email: colors_wind@outlook.com
License: UNKNOWN
Project-URL: Bug Tracker, https://github.com/ColorsWind/iTint/issues
Platform: UNKNOWN
Classifier: Programming Language :: Python :: 3
Classifier: License :: OSI Approved :: MIT License
Classifier: Operating System :: OS Independent
Requires-Python: >=3.7
Requires-Dist: numpy
Requires-Dist: pillow
Requires-Dist: pyside2
